rt_hat/FLOWCACHE.py
rt_hat/FPGA.py
rt_hat/PHY.py
rt_hat/SIGGEN.py
rt_hat/TAS.py
rt_hat/__init__.py
rt_hat_inr-0.6.9.data/scripts/INR-config
rt_hat_inr-0.6.9.data/scripts/INR_FPGA_license
rt_hat_inr-0.6.9.data/scripts/INR_FPGA_status
rt_hat_inr-0.6.9.data/scripts/INR_FlowCache
rt_hat_inr-0.6.9.data/scripts/INR_PHYd
rt_hat_inr-0.6.9.data/scripts/INR_PHYd_force_both_single
rt_hat_inr-0.6.9.data/scripts/INR_PHYd_uc0
rt_hat_inr-0.6.9.data/scripts/INR_change_bitstream
rt_hat_inr-0.6.9.dist-info/LICENSE
rt_hat_inr-0.6.9.dist-info/METADATA
rt_hat_inr-0.6.9.dist-info/WHEEL
rt_hat_inr-0.6.9.dist-info/top_level.txt
rt_hat_inr-0.6.9.dist-info/RECORD
