Metadata-Version: 2.1
Name: rt-hat-inr
Version: 0.6.9
Summary: RealtimeHAT control
Home-page: https://github.com/InnoRoute/RealtimeHAT
Author: Marian Ulbricht
Author-email: ulbricht@innoroute.de
Project-URL: Bug Tracker, https://github.com/InnoRoute/RealtimeHAT/issues
Classifier: Programming Language :: Python :: 3
Classifier: License :: OSI Approved :: MIT License
Classifier: Operating System :: OS Independent
Requires-Python: >=3.6
License-File: LICENSE
Requires-Dist: npyscreen
Requires-Dist: wget
Requires-Dist: configobj
Requires-Dist: goto-statement
Requires-Dist: transitions
Requires-Dist: asyncio
